llama_index/readers/oracleai/__init__.py
llama_index/readers/oracleai/base.py
llama_index_readers_oracleai-0.3.1.dist-info/METADATA
llama_index_readers_oracleai-0.3.1.dist-info/WHEEL
llama_index_readers_oracleai-0.3.1.dist-info/licenses/LICENSE
llama_index_readers_oracleai-0.3.1.dist-info/RECORD
